marsh_schema_piapia/__init__.py
marsh_schema_piapia/base_schema.py
marsh_schema_piapia/cmd.py
tests/__init__.py
tests/test_base_schema.py
marsh_schema_piapia-0.0.2.dist-info/METADATA
marsh_schema_piapia-0.0.2.dist-info/WHEEL
marsh_schema_piapia-0.0.2.dist-info/entry_points.txt
marsh_schema_piapia-0.0.2.dist-info/top_level.txt
marsh_schema_piapia-0.0.2.dist-info/RECORD
